imageutil/__init__.py
imageutil/metadata.py
python_imageutil-0.0.0.dist-info/LICENSE.txt
python_imageutil-0.0.0.dist-info/METADATA
python_imageutil-0.0.0.dist-info/WHEEL
python_imageutil-0.0.0.dist-info/top_level.txt
python_imageutil-0.0.0.dist-info/RECORD
