Metadata-Version: 2.1
Name: python-imageutil
Version: 0.0.0
Summary: high-level image operations.
Home-page: https://github.com/fabiocaccamo/python-imageutil
Download-URL: https://github.com/fabiocaccamo/python-imageutil/releases
Author: Fabio Caccamo
Author-email: fabio.caccamo@gmail.com
Maintainer: Fabio Caccamo
Maintainer-email: fabio.caccamo@gmail.com
License: MIT
Project-URL: Documentation, https://github.com/fabiocaccamo/python-imageutil#readme
Project-URL: Issues, https://github.com/fabiocaccamo/python-imageutil/issues
Project-URL: Funding, https://github.com/sponsors/fabiocaccamo/
Project-URL: Twitter, https://twitter.com/fabiocaccamo
Keywords: python,image,util,utils,utility,utilities
Classifier: Development Status :: 5 - Production/Stable
Classifier: Environment :: MacOS X
Classifier: Environment :: Web Environment
Classifier: Intended Audience :: Developers
Classifier: Intended Audience :: System Administrators
Classifier: License :: OSI Approved :: MIT License
Classifier: Natural Language :: English
Classifier: Operating System :: OS Independent
Classifier: Programming Language :: Python :: 3
Classifier: Programming Language :: Python :: 3.8
Classifier: Programming Language :: Python :: 3.9
Classifier: Programming Language :: Python :: 3.10
Classifier: Programming Language :: Python :: 3.11
Classifier: Programming Language :: Python :: Implementation :: PyPy
Classifier: Topic :: Desktop Environment :: File Managers
Classifier: Topic :: Software Development :: Build Tools
Classifier: Topic :: Software Development :: Libraries :: Python Modules
Classifier: Topic :: System :: Filesystems
Classifier: Topic :: Utilities
License-File: LICENSE.txt
